pyjelly/__init__.py
pyjelly/errors.py
pyjelly/options.py
pyjelly/_proto/grpc.proto
pyjelly/_proto/patch.proto
pyjelly/_proto/rdf.proto
pyjelly/integrations/__init__.py
pyjelly/integrations/generic/__init__.py
pyjelly/integrations/generic/generic_sink.py
pyjelly/integrations/generic/parse.py
pyjelly/integrations/generic/serialize.cpython-311-x86_64-linux-gnu.so
pyjelly/integrations/generic/serialize.py
pyjelly/integrations/rdflib/__init__.py
pyjelly/integrations/rdflib/parse.py
pyjelly/integrations/rdflib/serialize.py
pyjelly/jelly/__init__.py
pyjelly/jelly/rdf_pb2.py
pyjelly/jelly/rdf_pb2.pyi
pyjelly/parse/__init__.py
pyjelly/parse/decode.cpython-311-x86_64-linux-gnu.so
pyjelly/parse/decode.py
pyjelly/parse/ioutils.cpython-311-x86_64-linux-gnu.so
pyjelly/parse/ioutils.py
pyjelly/parse/lookup.cpython-311-x86_64-linux-gnu.so
pyjelly/parse/lookup.py
pyjelly/serialize/__init__.py
pyjelly/serialize/encode.cpython-311-x86_64-linux-gnu.so
pyjelly/serialize/encode.py
pyjelly/serialize/flows.py
pyjelly/serialize/ioutils.cpython-311-x86_64-linux-gnu.so
pyjelly/serialize/ioutils.py
pyjelly/serialize/lookup.cpython-311-x86_64-linux-gnu.so
pyjelly/serialize/lookup.py
pyjelly/serialize/streams.cpython-311-x86_64-linux-gnu.so
pyjelly/serialize/streams.py
pyjelly-0.7.1.dist-info/METADATA
pyjelly-0.7.1.dist-info/WHEEL
pyjelly-0.7.1.dist-info/entry_points.txt
pyjelly-0.7.1.dist-info/licenses/LICENSE
pyjelly-0.7.1.dist-info/RECORD
