Metadata-Version: 2.4
Name: pyjelly
Version: 0.7.1
Summary: Jelly-RDF implementation for Python
Project-URL: Homepage, https://w3id.org/jelly/pyjelly
Project-URL: Documentation, https://w3id.org/jelly/pyjelly
Project-URL: Repository, https://github.com/Jelly-RDF/pyjelly
Project-URL: Issues, https://github.com/Jelly-RDF/pyjelly/issues
Project-URL: Changelog, https://github.com/Jelly-RDF/pyjelly/releases
Author-email: "NeverBlink et al." <contact@neverblink.eu>
License-Expression: Apache-2.0
License-File: LICENSE
Keywords: Jelly,Knowledge graph,RDF,Serialization format
Classifier: Development Status :: 4 - Beta
Classifier: Environment :: Console
Classifier: Environment :: Plugins
Classifier: Intended Audience :: Developers
Classifier: Intended Audience :: Information Technology
Classifier: License :: OSI Approved :: Apache Software License
Classifier: Programming Language :: Python :: 3
Classifier: Programming Language :: Python :: 3.10
Classifier: Programming Language :: Python :: 3.11
Classifier: Programming Language :: Python :: 3.12
Classifier: Programming Language :: Python :: 3.13
Classifier: Programming Language :: Python :: 3.14
Classifier: Topic :: Database
Classifier: Topic :: File Formats
Classifier: Topic :: Software Development :: Libraries
Classifier: Topic :: Software Development :: Libraries :: Python Modules
Requires-Python: <3.15,>=3.10
Requires-Dist: mypy-extensions>=1.0.0
Requires-Dist: protobuf>=6.30.0
Requires-Dist: typing-extensions>=4.12.2
Provides-Extra: rdflib
Requires-Dist: rdflib>=7.1.4; extra == 'rdflib'
